flask_performance/__init__.py
flask_performance/_compat.py
flask_performance/performance_collector.py
Flask_Performance-0.0.6.dist-info/LICENSE
Flask_Performance-0.0.6.dist-info/METADATA
Flask_Performance-0.0.6.dist-info/WHEEL
Flask_Performance-0.0.6.dist-info/top_level.txt
Flask_Performance-0.0.6.dist-info/RECORD
