Metadata-Version: 2.1
Name: Flask-Performance
Version: 0.0.6
Summary: A Flask extension to monitoring every REAL api request and collect it's performance in REAL-time.
Home-page: https://github.com/SpaceBoxer/flask-performance
Author: Spacebox(盒子空间) Team
Author-email: spacebox@spacebox.fun
License: UNKNOWN
Platform: UNKNOWN
Classifier: Programming Language :: Python :: 3
Classifier: License :: OSI Approved :: MIT License
Classifier: Operating System :: OS Independent
Requires-Dist: flask
Requires-Dist: requests
